pytctracer/__init__.py
pytctracer/analyser.py
pytctracer/cli.py
pytctracer/tracer.py
pytctracer/config/__init__.py
pytctracer/config/config.py
pytctracer/config/constants/__init__.py
pytctracer/config/constants/classification_type.py
pytctracer/config/constants/event_type.py
pytctracer/config/constants/function_type.py
pytctracer/config/constants/instruction_opname.py
pytctracer/config/constants/level_type.py
pytctracer/config/constants/metric_score_type.py
pytctracer/config/constants/technique_parameter.py
pytctracer/config/constants/technique_threshold.py
pytctracer/config/constants/testing_method_event_type.py
pytctracer/config/constants/trace_data_header.py
pytctracer/config/constants/trace_data_variable.py
pytctracer/evaluation/__init__.py
pytctracer/evaluation/classify_predictions.py
pytctracer/evaluation/evaluate_predictions.py
pytctracer/evaluation/metrics/__init__.py
pytctracer/evaluation/metrics/area_under_curve.py
pytctracer/evaluation/metrics/arg_name_to_metric_mapper.py
pytctracer/evaluation/metrics/f1.py
pytctracer/evaluation/metrics/false_negatives.py
pytctracer/evaluation/metrics/false_positives.py
pytctracer/evaluation/metrics/mean_average_precision.py
pytctracer/evaluation/metrics/metric.py
pytctracer/evaluation/metrics/precision.py
pytctracer/evaluation/metrics/recall.py
pytctracer/evaluation/metrics/true_positives.py
pytctracer/io/__init__.py
pytctracer/io/input/__init__.py
pytctracer/io/input/from_file.py
pytctracer/io/output/__init__.py
pytctracer/io/output/to_display.py
pytctracer/io/output/to_file.py
pytctracer/parsing/__init__.py
pytctracer/parsing/find_class_level_calls.py
pytctracer/parsing/find_class_level_names.py
pytctracer/parsing/find_function_level_calls.py
pytctracer/parsing/find_function_level_names.py
pytctracer/parsing/functions_called_before_assert.py
pytctracer/techniques/__init__.py
pytctracer/techniques/arg_name_to_technique_mapper.py
pytctracer/techniques/combined.py
pytctracer/techniques/last_call_before_assert.py
pytctracer-0.2.4.dist-info/METADATA
pytctracer-0.2.4.dist-info/WHEEL
pytctracer-0.2.4.dist-info/entry_points.txt
pytctracer-0.2.4.dist-info/top_level.txt
pytctracer-0.2.4.dist-info/RECORD
